ComicallyDumb/__init__.py
ComicallyDumb-0.1.0.dist-info/METADATA
ComicallyDumb-0.1.0.dist-info/WHEEL
ComicallyDumb-0.1.0.dist-info/top_level.txt
ComicallyDumb-0.1.0.dist-info/RECORD
